{
	"id": "webdav",
	"name": "WebDav",
	"layer": "building-blocks",
	"itemKind": "tool",
	"description": {
		"de": "Protokoll für den Dateizugriff über das Internet",
		"en": "WebDAV (Web Distributed Authoring and Versioning) is a protocol for file access and management over the internet."
	},
	"oss": true,
	"tags": [],
	"sovereigntyCriteria": {
		"openSource": true,
		"euHeadquartered": false,
		"hasAudit": false,
		"permissiveLicense": true,
		"matureProject": true,
		"selfHostable": true,
		"dataPortability": true,
		"openStandards": true,
		"noTelemetryByDefault": true,
		"ownerType": "independentConsortium"
	},
	"homepage": "https://www.rfc-editor.org/rfc/rfc4918",
	"license": "IETF",
	"lastResearchDate": "2026-05-02",
	"researchSources": [
		{
			"type": "url",
			"url": "https://www.rfc-editor.org/rfc/rfc4918"
		},
		{
			"type": "url",
			"url": "https://datatracker.ietf.org/doc/html/rfc4918"
		}
	]
}
